pyriform.py
pyriform-0.5.dist-info/DESCRIPTION.rst
pyriform-0.5.dist-info/METADATA
pyriform-0.5.dist-info/RECORD
pyriform-0.5.dist-info/WHEEL
pyriform-0.5.dist-info/metadata.json
pyriform-0.5.dist-info/namespace_packages.txt
pyriform-0.5.dist-info/top_level.txt
