Metadata-Version: 2.0
Name: pyriform
Version: 0.5
Summary: Connect the requests library to your WSGI app without using sockets.
Home-page: https://github.com/the-allanc/pyriform/
Author: Allan Crooks
Author-email: allan@increment.one
License: MIT
Keywords: requests,wsgi
Platform: UNKNOWN
Classifier: Development Status :: 4 - Beta
Classifier: Intended Audience :: Developers
Classifier: License :: OSI Approved :: MIT License
Classifier: Operating System :: OS Independent
Classifier: Programming Language :: Python :: 2.7
Classifier: Programming Language :: Python :: 3
Classifier: Topic :: Software Development :: Libraries
Classifier: Topic :: Software Development :: Libraries :: Python Modules
Classifier: Topic :: Internet :: WWW/HTTP :: WSGI :: Middleware
Requires-Python: >=2.7
Requires-Dist: requests
Requires-Dist: six
Requires-Dist: webtest
Provides-Extra: docs
Requires-Dist: allanc-sphinx[yeen] (>=0.2); extra == 'docs'
Requires-Dist: collective.checkdocs; extra == 'docs'
Requires-Dist: jaraco.packaging (>=3.2); extra == 'docs'
Requires-Dist: rst.linker (>=1.9); extra == 'docs'
Requires-Dist: sphinx; extra == 'docs'
Provides-Extra: testing
Requires-Dist: cherrypy; extra == 'testing'
Requires-Dist: httpbin; extra == 'testing'
Requires-Dist: pytest (>=2.8); extra == 'testing'
Requires-Dist: pytest-sugar; extra == 'testing'
